CHANGELOG.rst
databricks_dbapi/__init__.py
databricks_dbapi/_version.py
databricks_dbapi/hive.py
databricks_dbapi/odbc.py
databricks_dbapi/sqlalchemy_dialects/__init__.py
databricks_dbapi/sqlalchemy_dialects/base.py
databricks_dbapi/sqlalchemy_dialects/hive.py
databricks_dbapi/sqlalchemy_dialects/odbc.py
databricks_dbapi-0.6.0.dist-info/entry_points.txt
databricks_dbapi-0.6.0.dist-info/LICENSE.txt
databricks_dbapi-0.6.0.dist-info/WHEEL
databricks_dbapi-0.6.0.dist-info/METADATA
databricks_dbapi-0.6.0.dist-info/RECORD
