Metadata-Version: 2.1
Name: databricks-dbapi
Version: 0.6.0
Summary: A DBAPI 2.0 interface and SQLAlchemy dialect for Databricks interactive clusters.
Home-page: https://github.com/crflynn/databricks-dbapi
License: MIT
Keywords: databricks,hive,dbapi,sqlalchemy,dialect
Author: Christopher Flynn
Author-email: crf204@gmail.com
Requires-Python: >=2.7, !=3.0.*, !=3.1.*, !=3.2.*, !=3.3.*, !=3.4.*
Classifier: License :: OSI Approved :: MIT License
Classifier: Natural Language :: English
Classifier: Programming Language :: Python :: 2
Classifier: Programming Language :: Python :: 2.7
Classifier: Programming Language :: Python :: 3
Classifier: Programming Language :: Python :: 3.5
Classifier: Programming Language :: Python :: 3.6
Classifier: Programming Language :: Python :: 3.7
Classifier: Programming Language :: Python :: 3.8
Classifier: Programming Language :: Python :: 3.9
Classifier: Programming Language :: Python :: Implementation :: CPython
Classifier: Topic :: Database
Classifier: Topic :: Database :: Front-Ends
Provides-Extra: hive
Provides-Extra: odbc
Provides-Extra: sqlalchemy
Requires-Dist: pyhive (>=0.6.1,<0.7.0); extra == "hive"
Requires-Dist: pyodbc (>=4.0.30,<5.0.0); extra == "odbc"
Requires-Dist: sqlalchemy (>=1.3,<2.0); extra == "sqlalchemy"
Requires-Dist: thrift (>=0.15.0,<0.16.0); extra == "hive"
Project-URL: Documentation, https://github.com/crflynn/databricks-dbapi
Project-URL: Repository, https://github.com/crflynn/databricks-dbapi
